background_task_manager/__init__.py
background_task_manager/runner.py
BackgroundTaskManager-0.1.1581720775.dist-info/LICENSE.txt
BackgroundTaskManager-0.1.1581720775.dist-info/METADATA
BackgroundTaskManager-0.1.1581720775.dist-info/WHEEL
BackgroundTaskManager-0.1.1581720775.dist-info/top_level.txt
BackgroundTaskManager-0.1.1581720775.dist-info/RECORD
