Metadata-Version: 2.1
Name: BackgroundTaskManager
Version: 0.1.1581720775
Summary: BackgroundTaskManager
Home-page: https://github.com/JulianKimmig/BackgroundTaskManager
Author: Julian Kimmig
Author-email: julian-kimmig@gmx.net
License: UNKNOWN
Platform: UNKNOWN
Classifier: Programming Language :: Python :: 3
Classifier: License :: OSI Approved :: MIT License
Classifier: Operating System :: OS Independent
